README.md
setup.py
tileIndexPythonGenerator/__init__.py
tileIndexPythonGenerator/tileIndexPythonGenerator.py
tileIndexPythonGenerator.egg-info/PKG-INFO
tileIndexPythonGenerator.egg-info/SOURCES.txt
tileIndexPythonGenerator.egg-info/dependency_links.txt
tileIndexPythonGenerator.egg-info/top_level.txt