Metadata-Version: 1.1
Name: tileIndexPythonGenerator
Version: 0.0.0.8
Summary: Python module to generate a TileIndex
Home-page: https://github.com/Gabriel-Desharnais/TileIndexPythonGenerator
Author: Gabriel Desharnais
Author-email: gabriel.desharnais@hotmail.com
License: MIT
Keywords: mapserver mapfile tileindex
Platform: UNKNOWN
Classifier: Development Status :: 3 - Alpha
Classifier: Intended Audience :: Science/Research
Classifier: Topic :: Scientific/Engineering :: Atmospheric Science
Classifier: License :: OSI Approved :: MIT License
Classifier: Programming Language :: Python :: 3
Classifier: Programming Language :: Python :: 3.5
